xiuxian_info/__init__.py
xiuxian_info/download.py
xiuxian_info/draw_user_info.py
xiuxian_info/infoconfig.py
xiuxian_info/send_image_tool.py
xiuxian_info-0.31.dist-info/METADATA
xiuxian_info-0.31.dist-info/WHEEL
xiuxian_info-0.31.dist-info/top_level.txt
xiuxian_info-0.31.dist-info/RECORD
